_awscrt.cp38-win_amd64.pdb
_awscrt.cp38-win_amd64.pyd
awscrt/__init__.py
awscrt/_test.py
awscrt/auth.py
awscrt/cbor.py
awscrt/checksums.py
awscrt/common.py
awscrt/crypto.py
awscrt/exceptions.py
awscrt/http.py
awscrt/io.py
awscrt/mqtt.py
awscrt/mqtt5.py
awscrt/mqtt_request_response.py
awscrt/s3.py
awscrt/websocket.py
awscrt/aio/__init__.py
awscrt/aio/http.py
awscrt/eventstream/__init__.py
awscrt/eventstream/rpc.py
awscrt-0.31.1.dist-info/LICENSE
awscrt-0.31.1.dist-info/METADATA
awscrt-0.31.1.dist-info/NOTICE
awscrt-0.31.1.dist-info/WHEEL
awscrt-0.31.1.dist-info/top_level.txt
awscrt-0.31.1.dist-info/RECORD
