Metadata-Version: 2.1
Name: awscrt
Version: 0.31.1
Summary: A common runtime for AWS Python projects
Author-email: "Amazon Web Services, Inc" <aws-sdk-common-runtime@amazon.com>
License: Apache-2.0
Project-URL: github, https://github.com/awslabs/aws-crt-python
Project-URL: documentation, https://awslabs.github.io/aws-crt-python
Project-URL: issues, https://github.com/awslabs/aws-crt-python/issues
Project-URL: releasenotes, https://github.com/awslabs/aws-crt-python/releases
Classifier: Programming Language :: Python :: 3
Classifier: Operating System :: Microsoft :: Windows
Classifier: Operating System :: POSIX
Classifier: Operating System :: Unix
Classifier: Operating System :: MacOS
Requires-Python: >=3.8
License-File: LICENSE
License-File: NOTICE
Provides-Extra: dev
Requires-Dist: autopep8 >=2.3.1 ; extra == 'dev'
Requires-Dist: build >=1.2.2 ; extra == 'dev'
Requires-Dist: websockets >=13.1 ; extra == 'dev'
Requires-Dist: h2 ==4.1.0 ; extra == 'dev'
Requires-Dist: sphinx <7.3,>=7.2.6 ; (python_version >= "3.9") and extra == 'dev'
